Metadata-Version: 2.1
Name: vmware-vapi-common-client
Version: 2.52.0
Summary: VMware vAPI Common Services Client Bindings
Home-page: https://github.com/vmware/vsphere-automation-sdk-python
Author: Broadcom
License: License :: OSI Approved :: MIT License
Keywords: Broadcom,VCF,vSphere
Platform: UNKNOWN
Classifier: Development Status :: 5 - Production/Stable
Classifier: License :: OSI Approved :: MIT License
Classifier: Intended Audience :: Information Technology
Classifier: Intended Audience :: System Administrators
Classifier: Intended Audience :: Developers
Classifier: Environment :: No Input/Output (Daemon)
Classifier: Programming Language :: Python :: 3.8
Classifier: Programming Language :: Python :: 3.9
Classifier: Programming Language :: Python :: 3.10
Classifier: Programming Language :: Python :: 3.11
Classifier: Topic :: Software Development :: Libraries :: Python Modules
Classifier: Topic :: System :: Distributed Computing
Classifier: Operating System :: Microsoft :: Windows
Classifier: Operating System :: POSIX
Classifier: Operating System :: Unix
Classifier: Operating System :: MacOS
Requires-Dist: vmware-vapi-runtime (==2.52.0)
